odoo10_addon_website_sale_require_legal-10.0.1.0.0.99.dev3-py2.7-nspkg.pth
odoo/addons/website_sale_require_legal/README.rst
odoo/addons/website_sale_require_legal/__init__.py
odoo/addons/website_sale_require_legal/__manifest__.py
odoo/addons/website_sale_require_legal/controllers/__init__.py
odoo/addons/website_sale_require_legal/controllers/main.py
odoo/addons/website_sale_require_legal/demo/assets.xml
odoo/addons/website_sale_require_legal/i18n/de.po
odoo/addons/website_sale_require_legal/i18n/es.po
odoo/addons/website_sale_require_legal/i18n/hr.po
odoo/addons/website_sale_require_legal/i18n/it.po
odoo/addons/website_sale_require_legal/i18n/sl.po
odoo/addons/website_sale_require_legal/i18n/website_sale_require_legal.pot
odoo/addons/website_sale_require_legal/static/description/icon.png
odoo/addons/website_sale_require_legal/static/src/js/tour.js
odoo/addons/website_sale_require_legal/tests/__init__.py
odoo/addons/website_sale_require_legal/tests/test_ui.py
odoo/addons/website_sale_require_legal/views/website_sale.xml
odoo10_addon_website_sale_require_legal-10.0.1.0.0.99.dev3.dist-info/METADATA
odoo10_addon_website_sale_require_legal-10.0.1.0.0.99.dev3.dist-info/RECORD
odoo10_addon_website_sale_require_legal-10.0.1.0.0.99.dev3.dist-info/WHEEL
odoo10_addon_website_sale_require_legal-10.0.1.0.0.99.dev3.dist-info/namespace_packages.txt
odoo10_addon_website_sale_require_legal-10.0.1.0.0.99.dev3.dist-info/top_level.txt
