Metadata-Version: 2.1
Name: odoo10-addon-website-sale-require-legal
Version: 10.0.1.0.0.99.dev3
Summary: Force the user to accept legal tems to buy in the web shop
Home-page: https://github.com/OCA/e-commerce
Author: Tecnativa, Odoo Community Association (OCA)
Author-email: support@odoo-community.org
License: AGPL-3
Platform: UNKNOWN
Classifier: Programming Language :: Python
Classifier: Framework :: Odoo
Classifier: License :: OSI Approved :: GNU Affero General Public License v3
Requires-Python: ~=2.7
Requires-Dist: odoo10-addon-website-legal-page
Requires-Dist: odoo (<10.1dev,>=10.0)
